clipdetect/__init__.py
clipdetect/cli.py
clipdetect-0.1.4.dist-info/LICENSE
clipdetect-0.1.4.dist-info/WHEEL
clipdetect-0.1.4.dist-info/entry_points.txt
clipdetect-0.1.4.dist-info/METADATA
clipdetect-0.1.4.dist-info/RECORD
