Metadata-Version: 2.1
Name: clipdetect
Version: 0.1.4
Summary: 
License: MIT
Author: roedoejet
Author-email: hello@aidanpine.ca
Requires-Python: >=3.9
Classifier: License :: OSI Approved :: MIT License
Classifier: Programming Language :: Python :: 3
Classifier: Programming Language :: Python :: 3.9
Classifier: Programming Language :: Python :: 3.10
Classifier: Programming Language :: Python :: 3.11
Requires-Dist: loguru (>=0.6.0,<0.7.0)
Requires-Dist: numpy (>=1.22)
Requires-Dist: pympi-ling (>=1.70.2,<2.0.0)
Requires-Dist: pytest (>=7.2.1,<8.0.0)
Requires-Dist: rich (>=10.11.0)
Requires-Dist: scipy (>=1.10.0,<2.0.0)
Requires-Dist: shellingham (>=1.3.0)
Requires-Dist: tqdm (>=4.64.1,<5.0.0)
Requires-Dist: typer (>=0.9.0)
